TEMP_transform/__init__.py
TEMP_transform/bufr2geojson.py
TEMP_transform/data2bufr.py
TEMP_transform/resources/309052_mapping.json
TEMP_transform/resources/309053_mapping.json
TEMP_transform/resources/__init__.py
TEMP_transform/tempDecoder/__init__.py
TEMP_transform/tempDecoder/temp_decoder.py
TEMP_transform/tempDecoder/tpg.py
temp_transform-0.0.19.dist-info/METADATA
temp_transform-0.0.19.dist-info/WHEEL
temp_transform-0.0.19.dist-info/top_level.txt
temp_transform-0.0.19.dist-info/RECORD
